zoom_select_image_component/__init__.py
zoom_select_image_component/example.py
zoom_select_image_component/example_sa.py
zoom_select_image_component/frontend/build/asset-manifest.json
zoom_select_image_component/frontend/build/bootstrap.min.css
zoom_select_image_component/frontend/build/index.html
zoom_select_image_component/frontend/build/static/js/main.33ddc49b.js
zoom_select_image_component/frontend/build/static/js/main.33ddc49b.js.LICENSE.txt
zoom_select_image_component/frontend/build/static/js/main.33ddc49b.js.map
zoom_select_image_component/frontend/build/static/js/main.f32751a7.js
zoom_select_image_component/frontend/build/static/js/main.f32751a7.js.LICENSE.txt
zoom_select_image_component/frontend/build/static/js/main.f32751a7.js.map
zoom_select_image_component-0.0.7.dist-info/LICENSE
zoom_select_image_component-0.0.7.dist-info/METADATA
zoom_select_image_component-0.0.7.dist-info/WHEEL
zoom_select_image_component-0.0.7.dist-info/top_level.txt
zoom_select_image_component-0.0.7.dist-info/RECORD
