Metadata-Version: 2.1
Name: zoom-select-image-component
Version: 0.0.7
Summary: Streamlit component that allows you to zoom and select parts of an image for further analysis.
Home-page: UNKNOWN
Author: Alexander Christiansson
Author-email: alexander.christiansson@gmail.com
License: UNKNOWN
Platform: UNKNOWN
Requires-Python: >=3.7
License-File: LICENSE
Requires-Dist: streamlit >=0.63
Requires-Dist: pillow >=9.4.0
Provides-Extra: devel
Requires-Dist: wheel ; extra == 'devel'
Requires-Dist: pytest ==7.4.0 ; extra == 'devel'
Requires-Dist: playwright ==1.39.0 ; extra == 'devel'
Requires-Dist: requests ==2.31.0 ; extra == 'devel'
Requires-Dist: pytest-playwright-snapshot ==1.0 ; extra == 'devel'
Requires-Dist: pytest-rerunfailures ==12.0 ; extra == 'devel'
